ben_chem_tools/__init__.py
ben_chem_tools/geometries.py
ben_chem_tools/input_creation.py
ben_chem_tools-0.3.0.dist-info/WHEEL
ben_chem_tools-0.3.0.dist-info/entry_points.txt
ben_chem_tools-0.3.0.dist-info/METADATA
ben_chem_tools-0.3.0.dist-info/RECORD
