Metadata-Version: 2.3
Name: ben-chem-tools
Version: 0.3.0
Summary: common useful tools for computational chemistry
Author: Ben
Author-email: Ben <bennyp2494@gmail.com>
Requires-Dist: cclib>=1.8.1
Requires-Dist: matplotlib>=3.9.4
Requires-Dist: numpy>=2.0.2
Requires-Dist: pandas>=2.3.3
Requires-Dist: periodictable>=2.0.2
Requires-Dist: scipy>=1.13.1
Requires-Dist: seaborn>=0.13.2
Requires-Python: >=3.9
